{"date":"15.01.2019","bank":"PB","baseCurrency":980,"baseCurrencyLit":"UAH","exchangeRate":[{"baseCurrency":"UAH","saleRateNB":20.1534940,"purchaseRateNB":20.1534940},{"baseCurrency":"UAH","currency":"CAD","saleRateNB":21.1051800,"purchaseRateNB":21.1051800},{"baseCurrency":"UAH","currency":"CNY","saleRateNB":4.1413420,"purchaseRateNB":4.1413420},{"baseCurrency":"UAH","currency":"CZK","saleRateNB":1.2571790,"purchaseRateNB":1.2571790,"saleRate":1.2600000,"purchaseRate":1.1500000},{"baseCurrency":"UAH","currency":"DKK","saleRateNB":4.3053560,"purchaseRateNB":4.3053560},{"baseCurrency":"UAH","currency":"HUF","saleRateNB":0.1000054,"purchaseRateNB":0.1000054},{"baseCurrency":"UAH","currency":"ILS","saleRateNB":7.6611630,"purchaseRateNB":7.6611630},{"baseCurrency":"UAH","currency":"JPY","saleRateNB":0.2592976,"purchaseRateNB":0.2592976},{"baseCurrency":"UAH","currency":"KZT","saleRateNB":0.0740800,"purchaseRateNB":0.0740800},{"baseCurrency":"UAH","currency":"MDL","saleRateNB":1.6361510,"purchaseRateNB":1.6361510},{"baseCurrency":"UAH","currency":"NOK","saleRateNB":3.2834780,"purchaseRateNB":3.2834780},{"baseCurrency":"UAH","currency":"SGD","saleRateNB":20.6973770,"purchaseRateNB":20.6973770},{"baseCurrency":"UAH","currency":"SEK","saleRateNB":3.1353110,"purchaseRateNB":3.1353110},{"baseCurrency":"UAH","currency":"CHF","saleRateNB":28.5439220,"purchaseRateNB":28.5439220,"saleRate":28.7000000,"purchaseRate":27.0000000},{"baseCurrency":"UAH","currency":"RUB","saleRateNB":0.4170700,"purchaseRateNB":0.4170700,"saleRate":0.4200000,"purchaseRate":0.3950000},{"baseCurrency":"UAH","currency":"GBP","saleRateNB":36.0000750,"purchaseRateNB":36.0000750,"saleRate":36.5000000,"purchaseRate":34.2000000},{"baseCurrency":"UAH","currency":"USD","saleRateNB":28.0236740,"purchaseRateNB":28.0236740,"saleRate":28.2000000,"purchaseRate":27.8000000},{"baseCurrency":"UAH","currency":"UZS","saleRateNB":0.0033200,"purchaseRateNB":0.0033200},{"baseCurrency":"UAH","currency":"BYN","saleRateNB":13.0088500,"purchaseRateNB":13.0088500},{"baseCurrency":"UAH","currency":"TMT","saleRateNB":7.9109330,"purchaseRateNB":7.9109330},{"baseCurrency":"UAH","currency":"AZN","saleRateNB":16.4845140,"purchaseRateNB":16.4845140},{"baseCurrency":"UAH","currency":"TRY","saleRateNB":5.0813150,"purchaseRateNB":5.0813150},{"baseCurrency":"UAH","currency":"EUR","saleRateNB":32.1347470,"purchaseRateNB":32.1347470,"saleRate":32.3000000,"purchaseRate":31.5500000},{"baseCurrency":"UAH","currency":"UAH","saleRateNB":1.0000000,"purchaseRateNB":1.0000000},{"baseCurrency":"UAH","currency":"GEL","saleRateNB":10.3445650,"purchaseRateNB":10.3445650},{"baseCurrency":"UAH","currency":"PLZ","saleRateNB":7.4862540,"purchaseRateNB":7.4862540,"saleRate":7.5500000,"purchaseRate":7.0500000}]}